pubchemquery/__init__.py
pubchemquery/app.py
pubchemquery/docs/__init__.py
pubchemquery/docs/api.py
pubchemquery/docs/config.py
pubchemquery/docs/util.py
PubChemQuery-1.5.0.dist-info/LICENSE
PubChemQuery-1.5.0.dist-info/METADATA
PubChemQuery-1.5.0.dist-info/WHEEL
PubChemQuery-1.5.0.dist-info/top_level.txt
PubChemQuery-1.5.0.dist-info/RECORD
