Metadata-Version: 2.1
Name: PubChemQuery
Version: 1.5.0
Summary: A Python Package for Accessing Chemical Information from PubChem (https://pubchem.ncbi.nlm.nih.gov/).
Author: Sina Gilassi
Author-email: <sina.gilassi@gmail.com>
License: MIT
Keywords: python,PubChem,PubChemAPI,PubChemQuery,pubchemquery
Classifier: Development Status :: 1 - Planning
Classifier: Intended Audience :: Education
Classifier: Programming Language :: Python :: 3
Classifier: Operating System :: Unix
Classifier: Operating System :: MacOS :: MacOS X
Classifier: Operating System :: Microsoft :: Windows
Requires-Python: >=3.6
License-File: LICENSE
Requires-Dist: pandas
Requires-Dist: pillow
Requires-Dist: requests
Requires-Dist: urllib3
